pod_rbf/__init__.py
pod_rbf/core.py
pod_rbf/decomposition.py
pod_rbf/io.py
pod_rbf/rbf.py
pod_rbf/shape_optimization.py
pod_rbf/types.py
pod_rbf-2.0.1.dist-info/licenses/LICENSE
pod_rbf-2.0.1.dist-info/METADATA
pod_rbf-2.0.1.dist-info/WHEEL
pod_rbf-2.0.1.dist-info/top_level.txt
pod_rbf-2.0.1.dist-info/RECORD
