Metadata-Version: 2.4
Name: pod_rbf
Version: 2.0.1
Summary: JAX-based POD-RBF for autodiff-enabled reduced order modeling.
Author-email: Kyle Beggs <beggskw@gmail.com>
License: MIT
Project-URL: Homepage, https://github.com/kylebeggs/POD-RBF
Project-URL: Repository, https://github.com/kylebeggs/POD-RBF
Classifier: Programming Language :: Python :: 3
Classifier: Programming Language :: Python :: 3.10
Classifier: Programming Language :: Python :: 3.11
Classifier: Programming Language :: Python :: 3.12
Classifier: License :: OSI Approved :: MIT License
Classifier: Operating System :: OS Independent
Requires-Python: >=3.10
License-File: LICENSE
Requires-Dist: jax>=0.4.0
Requires-Dist: jaxlib>=0.4.0
Requires-Dist: numpy
Requires-Dist: tqdm
Provides-Extra: dev
Requires-Dist: pytest>=7.0; extra == "dev"
Requires-Dist: pytest-cov; extra == "dev"
Dynamic: license-file
